pydbm/__init__.py
pydbm/contstant.py
pydbm/exceptions.py
pydbm/inspect_extra.py
pydbm/logging.py
pydbm/py.typed
pydbm/typing_extra.py
pydbm/database/__init__.py
pydbm/database/manager.py
pydbm/database/data_types/__init__.py
pydbm/database/data_types/base.py
pydbm/database/data_types/types.py
pydbm/models/__init__.py
pydbm/models/base.py
pydbm/models/meta.py
pydbm/models/fields/__init__.py
pydbm/models/fields/auto.py
pydbm/models/fields/base.py
pydbm/models/validators/__init__.py
pydbm/models/validators/builtin_types.py
pydbm/models/validators/compare.py
pythonic_dbm-0.6.0.dist-info/LICENSE
pythonic_dbm-0.6.0.dist-info/METADATA
pythonic_dbm-0.6.0.dist-info/WHEEL
pythonic_dbm-0.6.0.dist-info/top_level.txt
pythonic_dbm-0.6.0.dist-info/zip-safe
pythonic_dbm-0.6.0.dist-info/RECORD
