Metadata-Version: 2.1
Name: pythonic-dbm
Version: 0.6.0
Summary: Pydbm is a more pythonic way to use dbm.
Home-page: https://pydbm.hakancelik.dev/
Author: Hakan Celik
Author-email: hakancelikdev@gmail.com
License: GPL-3.0
Project-URL: Documentation, https://pydbm.hakancelik.dev/
Project-URL: Issues, https://github.com/hakancelikdev/pydbm/issues/
Project-URL: Changelog, https://pydbm.hakancelik.dev/changelog
Classifier: Development Status :: 3 - Alpha
Classifier: Intended Audience :: Developers
Classifier: License :: OSI Approved :: GNU General Public License v3 (GPLv3)
Classifier: Operating System :: OS Independent
Classifier: Programming Language :: Python
Classifier: Programming Language :: Python :: 3
Classifier: Programming Language :: Python :: 3 :: Only
Classifier: Programming Language :: Python :: 3.8
Classifier: Programming Language :: Python :: 3.9
Classifier: Programming Language :: Python :: 3.10
Classifier: Programming Language :: Python :: Implementation :: CPython
Classifier: Topic :: Software Development :: Libraries :: Python Modules
Requires-Python: >=3.8
License-File: LICENSE
Provides-Extra: docs
Requires-Dist: mkdocs (==1.4.2) ; extra == 'docs'
Requires-Dist: mkdocs-material (==8.5.11) ; extra == 'docs'
Requires-Dist: mkdocs-markdownextradata-plugin (==0.2.5) ; extra == 'docs'
Requires-Dist: mkdocs-minify-plugin (==0.6.2) ; extra == 'docs'
Requires-Dist: mkdocs-git-revision-date-localized-plugin (==1.1.0) ; extra == 'docs'
Requires-Dist: mike (==1.1.2) ; extra == 'docs'
Provides-Extra: tests
Requires-Dist: pytest (==7.2.0) ; extra == 'tests'
Requires-Dist: pytest-cov (==4.0.0) ; extra == 'tests'
